prothreat/__init__.py
prothreat/__main__.py
prothreat-0.1.0.dist-info/LICENSE.txt
prothreat-0.1.0.dist-info/METADATA
prothreat-0.1.0.dist-info/WHEEL
prothreat-0.1.0.dist-info/entry_points.txt
prothreat-0.1.0.dist-info/top_level.txt
prothreat-0.1.0.dist-info/RECORD
