Metadata-Version: 2.1
Name: prothreat
Version: 0.1.0
Summary: TODO: write a description
Home-page: https://github.com/fmind/prothreat
Author: Médéric Hurier (fmind)
Author-email: fmind@fmind.me
License: LGPL-3.0
Keywords: sample package development
Platform: UNKNOWN
Classifier: Development Status :: 4 - Beta
Requires-Python: >=3.7
